template_magic/__init__.py
template_magic/jinja.py
template_magic/mako.py
template_ipython_magic-0.1.2.dist-info/WHEEL
template_ipython_magic-0.1.2.dist-info/METADATA
template_ipython_magic-0.1.2.dist-info/RECORD
